pylindol/__init__.py
pylindol/ca_certificates/GlobalSign RSA OV SSL CA 2018.pem
pylindol/cli.py
pylindol/config/__init__.py
pylindol/config/paths.py
pylindol/earthquake_info_scraper.py
pylindol/tests/__init__.py
pylindol/tests/test_certificate_handler.py
pylindol/tests/test_cli.py
pylindol/tests/test_earthquake_info_scraper.py
pylindol/utils/__init__.py
pylindol/utils/certificate_handler.py
pylindol-0.3.0.dist-info/WHEEL
pylindol-0.3.0.dist-info/entry_points.txt
pylindol-0.3.0.dist-info/METADATA
pylindol-0.3.0.dist-info/RECORD
