Metadata-Version: 2.3
Name: pylindol
Version: 0.3.0
Summary: A tool to download earthquake report information from the Philippine Institute of Volcanology and Seismology (PHIVOLCS) website.
Author: clnhrn
Author-email: clnhrn <herniacln@gmail.com>
License: MIT
Requires-Dist: beautifulsoup4>=4.14.2
Requires-Dist: certifi>=2024.0.0
Requires-Dist: click>=8.1.8
Requires-Dist: loguru>=0.7.3
Requires-Dist: lxml>=6.0.2
Requires-Dist: pandas>=2.3.3
Requires-Dist: requests>=2.32.5
Requires-Python: >=3.11
